LICENSE
README.md
cli.py
setup.cfg
setup.py
test/test_core.py
wgd/__init__.py
wgd/beast.py
wgd/cluster.py
wgd/codeml.py
wgd/core.py
wgd/mcmctree.py
wgd/mix.py
wgd/peak.py
wgd/postplot.py
wgd/ratecorrect.py
wgd/syn.py
wgd/tree.py
wgd/utils.py
wgd/viz.py
wgd.egg-info/PKG-INFO
wgd.egg-info/SOURCES.txt
wgd.egg-info/dependency_links.txt
wgd.egg-info/entry_points.txt
wgd.egg-info/requires.txt
wgd.egg-info/top_level.txt