Metadata-Version: 2.1
Name: wgd
Version: 2.0.32
Summary: wgd
Home-page: http://github.com/heche-psb/wgd
Author: Hengchi Chen
Author-email: heche@psb.vib-ugent.be
License: GPL
License-File: LICENSE
